{
	"tracks": [{
			"artist": "Artist 1",
			"title": "Artist 1 - Title 1",
			"url": "https://soundcloud.com/artist/track-name",
			"userID": [" <@432004354329935875>"]
		},
		{
			"artist": "Artist 2",
			"title": "Artist 2 - Title 2",
			"url": "https://soundcloud.com/artist/track-name",
			"userID": [" <@432004354329935875>", " <@159985870458322944>"]
		},
		{
			"artist": "Artist 3",
			"title": "Artist 3 - Title 3",
			"url": "https://soundcloud.com/artist/track-name",
			"userID": [" <@432004354329935875>"]
		},
		{
			"artist": "Artist 4",
			"title": "Artist 4 - Title 4",
			"url": "https://soundcloud.com/artist/track-name",
			"userID": [" <@432004354329935875>", " <@159985870458322944>"]
		},
		{
			"artist": "Artist 5",
			"title": "Artist 5 - Title 5",
			"url": "https://soundcloud.com/artist/track-name",
			"userID": [" <@432004354329935875>"]
		},
		{
			"artist": "Artist 6",
			"title": "Artist 6 - Title 6",
			"url": "https://soundcloud.com/artist/track-name",
			"userID": [" <@432004354329935875>", " <@159985870458322944>"]
		},
		{
			"artist": "Artist 7",
			"title": "Artist 7 - Title 7",
			"url": "https://soundcloud.com/artist/track-name",
			"userID": [" <@432004354329935875>"]
		},
		{
			"artist": "Artist 8",
			"title": "Artist 8 - Title 8",
			"url": "https://soundcloud.com/artist/track-name",
			"userID": [" <@432004354329935875>", " <@159985870458322944>"]
		}
	],
	"duel1": [{
			"artist": "Artist 1",
			"title": "Artist 1 - Title 1",
			"url": "https://soundcloud.com/artist/track-name",
			"userID": [" <@432004354329935875>"]
		},
		{
			"artist": "Artist 2",
			"title": "Artist 2 - Title 2",
			"url": "https://soundcloud.com/artist/track-name",
			"userID": [" <@432004354329935875>", " <@159985870458322944>"]
		}
	],
	"duel2": [{
			"artist": "Artist 3",
			"title": "Artist 3 - Title 3",
			"url": "https://soundcloud.com/artist/track-name",
			"userID": [" <@432004354329935875>"]
		},
		{
			"artist": "Artist 4",
			"title": "Artist 4 - Title 4",
			"url": "https://soundcloud.com/artist/track-name",
			"userID": [" <@432004354329935875>", " <@159985870458322944>"]
		}
	],
	"duel3": [{
			"artist": "Artist 5",
			"title": "Artist 5 - Title 5",
			"url": "https://soundcloud.com/artist/track-name",
			"userID": [" <@432004354329935875>"]
		},
		{
			"artist": "Artist 6",
			"title": "Artist 6 - Title 6",
			"url": "https://soundcloud.com/artist/track-name",
			"userID": [" <@432004354329935875>", " <@159985870458322944>"]
		}
	],
	"duel4": [{
			"artist": "Artist 7",
			"title": "Artist 7 - Title 7",
			"url": "https://soundcloud.com/artist/track-name",
			"userID": [" <@432004354329935875>"]
		},
		{
			"artist": "Artist 8",
			"title": "Artist 8 - Title 8",
			"url": "https://soundcloud.com/artist/track-name",
			"userID": [" <@432004354329935875>", " <@159985870458322944>"]
		}
	],
	"semi1": [{
			"artist": null,
			"title": null,
			"url": null,
			"userID": null
		},
		{
			"artist": null,
			"title": null,
			"url": null,
			"userID": null
		}
	],
	"semi2": [{
			"artist": null,
			"title": null,
			"url": null,
			"userID": null
		},
		{
			"artist": null,
			"title": null,
			"url": null,
			"userID": null
		}
	],
	"final": [{
			"artist": null,
			"title": null,
			"url": null,
			"userID": null
		},
		{
			"artist": null,
			"title": null,
			"url": null,
			"userID": null
		}
	],
	"winner": {
		"artist": null,
		"title": null,
		"url": null,
		"userID": null
	},
	"progress": {
		"match": 0,
		"voteTime": 1435,
		"status": [
			[0, 0],
			[0, 0],
			[0, 0],
			[0, 0],
			[0, 0],
			[0, 0],
			[0, 0]
		]
	}
}
